kangtools/__init__.py
kangtools/commit_version_to_git.py
kangtools/creat_blog_post_git_commit_push.py
kangtools/upgrade_pypi_package_pip_install.py
kangtools/version_control.py
kangtools-0.0.20.dist-info/METADATA
kangtools-0.0.20.dist-info/WHEEL
kangtools-0.0.20.dist-info/entry_points.txt
kangtools-0.0.20.dist-info/top_level.txt
kangtools-0.0.20.dist-info/RECORD
