Metadata-Version: 2.1
Name: kangtools
Version: 0.0.20
Summary: A Python package for version control.
Author: xiaowen kang
Author-email: kangxiaowen@gmail.com
License: LICENSE
